ldapdomaindump/__init__.py
ldapdomaindump/__main__.py
ldapdomaindump/convert.py
ldapdomaindump/pretty.py
ldapdomaindump/style.css
ldapdomaindump-0.9.4.data/scripts/ldapdomaindump
ldapdomaindump-0.9.4.data/scripts/ldd2bloodhound
ldapdomaindump-0.9.4.data/scripts/ldd2pretty
ldapdomaindump-0.9.4.dist-info/DESCRIPTION.rst
ldapdomaindump-0.9.4.dist-info/METADATA
ldapdomaindump-0.9.4.dist-info/RECORD
ldapdomaindump-0.9.4.dist-info/WHEEL
ldapdomaindump-0.9.4.dist-info/metadata.json
ldapdomaindump-0.9.4.dist-info/top_level.txt
